peridio_evk/__init__.py
peridio_evk/cli.py
peridio_evk/crypto.py
peridio_evk/log.py
peridio_evk/product.py
peridio_evk/releases.py
peridio_evk/uboot_env.py
peridio_evk/utils.py
peridio_evk/commands/__init__.py
peridio_evk/commands/devices.py
peridio_evk/commands/initialize.py
peridio_evk-0.1.8.dist-info/licenses/LICENSE.txt
peridio_evk-0.1.8.dist-info/METADATA
peridio_evk-0.1.8.dist-info/WHEEL
peridio_evk-0.1.8.dist-info/entry_points.txt
peridio_evk-0.1.8.dist-info/top_level.txt
peridio_evk-0.1.8.dist-info/RECORD
