Metadata-Version: 2.4
Name: peridio_evk
Version: 0.1.8
Summary: The Peridio Evaluation Kit
Home-page: https://github.com/peridio/peridio-evk
Author: Peridio Developers
Author-email: support@peridio.com
Classifier: Programming Language :: Python :: 3
Classifier: License :: OSI Approved :: MIT License
Classifier: Operating System :: OS Independent
License-File: LICENSE.txt
Requires-Dist: click
Requires-Dist: cryptography
Requires-Dist: uboot
Requires-Dist: docker
Dynamic: author
Dynamic: author-email
Dynamic: classifier
Dynamic: description
Dynamic: description-content-type
Dynamic: home-page
Dynamic: license-file
Dynamic: requires-dist
Dynamic: summary
